ja_itaiji/__init__.py
ja_itaiji/ja_itaiji.py
ja_itaiji/data/term/.DS_Store
ja_itaiji/data/term/ja-itaiji.json
ja_itaiji-1.0.2.dist-info/LICENSE
ja_itaiji-1.0.2.dist-info/METADATA
ja_itaiji-1.0.2.dist-info/WHEEL
ja_itaiji-1.0.2.dist-info/top_level.txt
ja_itaiji-1.0.2.dist-info/RECORD
