Metadata-Version: 2.1
Name: ja-itaiji
Version: 1.0.2
Summary: ja-itaiji: handling Japanese 異体字 (itaiji), which are variant forms of kanji characters
Home-page: https://github.com/RjChiba/ja_itaiji
Download-URL: https://github.com/RjChiba/ja_itaiji
Author: Ryuji Chiba
Author-email: manchuria.museum@gmail.com
Maintainer: Ryuji Chiba
Maintainer-email: manchuria.museum@gmail.com
License: MIT
Classifier: Development Status :: 1 - Planning
Classifier: Environment :: Console
Classifier: Intended Audience :: Science/Research
Classifier: License :: OSI Approved :: MIT License
Classifier: Natural Language :: Japanese
Classifier: Programming Language :: Python :: 3
Classifier: Topic :: Text Processing :: General
Requires-Python: >=3.9
License-File: LICENSE
